pandas_cobol_io/__init__.py
pandas_cobol_io/py.typed
pandas_cobol_io-0.1.0.dist-info/METADATA
pandas_cobol_io-0.1.0.dist-info/WHEEL
pandas_cobol_io-0.1.0.dist-info/licenses/LICENSE
pandas_cobol_io-0.1.0.dist-info/RECORD
