Metadata-Version: 2.4
Name: pandas-cobol-io
Version: 0.1.0
Summary: Pandas extension for COBOL-style fixed-width files handling multibyte encoding.
Author-email: jianwu <yi1meir4@gmail.com>
License-Expression: MIT
License-File: LICENSE
Requires-Python: >=3.10
Requires-Dist: pandas
